toycoronagraph/__init__.py
toycoronagraph/main.py
toycoronagraph/para.py
toycoronagraph/planet.py
toycoronagraph/psf.py
toycoronagraph/tool.py
toycoronagraph/toycoronagraph_para.py
toycoronagraph/example_data/example.fits
toycoronagraph-1.6.2.dist-info/LICENSE
toycoronagraph-1.6.2.dist-info/METADATA
toycoronagraph-1.6.2.dist-info/WHEEL
toycoronagraph-1.6.2.dist-info/top_level.txt
toycoronagraph-1.6.2.dist-info/RECORD
