Metadata-Version: 2.1
Name: toycoronagraph
Version: 1.6.2
Summary: Toy!!
Home-page: https://github.com/dreamjade/Toy_Coronagraph
Author: dreamjade
Author-email: 
License: MIT
Keywords: Toy Coronagraph
Classifier: Development Status :: 3 - Alpha
Classifier: Intended Audience :: Science/Research
Classifier: Topic :: Scientific/Engineering :: Astronomy
Classifier: License :: OSI Approved :: MIT License
Classifier: Programming Language :: Python :: 3.11
License-File: LICENSE
Requires-Dist: astropy (>=4)
Requires-Dist: numpy
Requires-Dist: matplotlib
Requires-Dist: scikit-image
Requires-Dist: pysynphot
Requires-Dist: hcipy
Requires-Dist: ffmpeg-python
